diablo2_mod_sql/__init__.py
diablo2_mod_sql/data/__init__.py
diablo2_mod_sql/data/d2string.py
diablo2_mod_sql/data/database.py
diablo2_mod_sql/data/table.py
diablo2_mod_sql/data/d2txt/__init__.py
diablo2_mod_sql/data/d2txt/column_spec.py
diablo2_mod_sql/sql/__init__.py
diablo2_mod_sql/sql/operand.py
diablo2_mod_sql/sql/statement.py
diablo2_mod_sql-1.0.0.dist-info/METADATA
diablo2_mod_sql-1.0.0.dist-info/WHEEL
diablo2_mod_sql-1.0.0.dist-info/licenses/LICENSE
diablo2_mod_sql-1.0.0.dist-info/RECORD
